HogProf/__init__.py
HogProf/lshbuilder.py
HogProf/orthoxml.py
HogProf/profiler.py
HogProf/build/lib/notebooks/__init__.py
HogProf/build/lib/pyoma/__init__.py
HogProf/build/lib/pyoma/browser/KmerEncoder.py
HogProf/build/lib/pyoma/browser/OrthoXMLSplitter.py
HogProf/build/lib/pyoma/browser/__init__.py
HogProf/build/lib/pyoma/browser/check_db_consistency.py
HogProf/build/lib/pyoma/browser/convert.py
HogProf/build/lib/pyoma/browser/convert_omastandalone.py
HogProf/build/lib/pyoma/browser/db.py
HogProf/build/lib/pyoma/browser/geneontology.py
HogProf/build/lib/pyoma/browser/homoeologs.py
HogProf/build/lib/pyoma/browser/linkout.py
HogProf/build/lib/pyoma/browser/locus_parser.py
HogProf/build/lib/pyoma/browser/models.py
HogProf/build/lib/pyoma/browser/synteny.py
HogProf/build/lib/pyoma/browser/tablefmt.py
HogProf/build/lib/tests/__init__.py
HogProf/build/lib/tests/test_hashutils.py
HogProf/build/lib/tests/test_hpputils.py
HogProf/build/lib/tests/test_profiler.py
HogProf/build/lib/utils/__init__.py
HogProf/build/lib/utils/config_utils.py
HogProf/build/lib/utils/files_utils.py
HogProf/build/lib/utils/goatools_utils.py
HogProf/build/lib/utils/hashutils.py
HogProf/build/lib/utils/preprocess_config.py
HogProf/build/lib/utils/pyhamutils.py
HogProf/notebooks/__init__.py
HogProf/tests/__init__.py
HogProf/tests/test_hashutils.py
HogProf/tests/test_hpputils.py
HogProf/tests/test_profiler.py
HogProf/utils/__init__.py
HogProf/utils/files_utils.py
HogProf/utils/goautils.py
HogProf/utils/hashutils.py
HogProf/utils/pyhamutils.py
HogProf-0.0.11.dist-info/LICENSE
HogProf-0.0.11.dist-info/METADATA
HogProf-0.0.11.dist-info/WHEEL
HogProf-0.0.11.dist-info/top_level.txt
HogProf-0.0.11.dist-info/RECORD
