Metadata-Version: 2.1
Name: HogProf
Version: 0.0.11
Summary: Phylogenetic Profiling with OMA and minhashing
Author-email: Dave Moi <dmoi@unil.ch>
License: MIT License
Project-URL: Homepage, https://github.com/DessimozLab/HogProf
Project-URL: Bug Tracker, https://github.com/DessimozLab/HogProf/issues
Project-URL: Docs, https://dessimozlab.github.io/HogProf/
Classifier: Programming Language :: Python :: 3
Classifier: License :: OSI Approved :: MIT License
Classifier: Operating System :: OS Independent
Requires-Python: >=3.7
License-File: LICENSE
Requires-Dist: biopython
Requires-Dist: certifi
Requires-Dist: chardet
Requires-Dist: datasketch
Requires-Dist: ete3
Requires-Dist: future
Requires-Dist: goatools
Requires-Dist: h5py
Requires-Dist: idna
Requires-Dist: lxml
Requires-Dist: numexpr
Requires-Dist: numpy
Requires-Dist: pandas
Requires-Dist: pyham >=1.1.10
Requires-Dist: pyoma
Requires-Dist: pyopa
Requires-Dist: python-dateutil
Requires-Dist: pytz
Requires-Dist: requests
Requires-Dist: scipy
Requires-Dist: six
Requires-Dist: tables
Requires-Dist: urllib3
Requires-Dist: tqdm
